cuprum/__init__.py
cuprum/_observability.py
cuprum/_pipeline_internals.py
cuprum/_pipeline_spawn.py
cuprum/_pipeline_streams.py
cuprum/_pipeline_wait.py
cuprum/_process_lifecycle.py
cuprum/_streams.py
cuprum/_testing.py
cuprum/adapters/__init__.py
cuprum/adapters/logging_adapter.py
cuprum/adapters/metrics_adapter.py
cuprum/adapters/tracing_adapter.py
cuprum/catalogue.py
cuprum/context.py
cuprum/events.py
cuprum/logging_hooks.py
cuprum/program.py
cuprum/sh.py
cuprum/unittests/test_adapters.py
cuprum/unittests/test_catalogue.py
cuprum/unittests/test_context.py
cuprum/unittests/test_logging_hook.py
cuprum/unittests/test_observe.py
cuprum/unittests/test_pipeline.py
cuprum/unittests/test_public_api.py
cuprum/unittests/test_safe_cmd_run.py
cuprum/unittests/test_sh.py
cuprum-0.1.0.dist-info/WHEEL
cuprum-0.1.0.dist-info/METADATA
cuprum-0.1.0.dist-info/RECORD
