Metadata-Version: 2.3
Name: cuprum
Version: 0.1.0
Summary: cuprum package
Author: Payton McIntosh
Author-email: Payton McIntosh <pmcintosh@df12.net>
License: ISC
Requires-Python: >=3.12
Project-URL: Homepage, https://df12.studio/docs.html
Project-URL: Repository, https://github.com/leynos/cuprum
